your_telegraph-0.2.1.dist-info/licenses/LICENSE
ytelegraph/__init__.py
ytelegraph/account.py
ytelegraph/api.py
ytelegraph/md_to_dom.py
your_telegraph-0.2.1.dist-info/METADATA
your_telegraph-0.2.1.dist-info/WHEEL
your_telegraph-0.2.1.dist-info/top_level.txt
your_telegraph-0.2.1.dist-info/RECORD
