Metadata-Version: 2.4
Name: your-telegraph
Version: 0.2.1
Summary: A simple Python wrapper for the Telegraph API
Home-page: https://github.com/alterxyz/ytelegraph
Author: alterxyz
Author-email: 88554920+alterxyz@users.noreply.github.com
Project-URL: Bug Tracker, https://github.com/alterxyz/ytelegraph/issues
Project-URL: Documentation, https://github.com/alterxyz/ytelegraph/blob/main/README.md
Project-URL: Source Code, https://github.com/alterxyz/ytelegraph
Keywords: telegraph api wrapper markdown publishing
Classifier: Development Status :: 3 - Alpha
Classifier: Intended Audience :: Developers
Classifier: License :: OSI Approved :: MIT License
Classifier: Programming Language :: Python :: 3
Classifier: Programming Language :: Python :: 3.8
Classifier: Programming Language :: Python :: 3.9
Classifier: Programming Language :: Python :: 3.10
Classifier: Programming Language :: Python :: 3.11
Classifier: Programming Language :: Python :: 3.12
Classifier: Operating System :: OS Independent
Classifier: Topic :: Internet :: WWW/HTTP
Classifier: Topic :: Software Development :: Libraries :: Python Modules
Requires-Python: >=3.8
License-File: LICENSE
Requires-Dist: requests
Requires-Dist: beautifulsoup4
Requires-Dist: Markdown
Dynamic: author
Dynamic: author-email
Dynamic: classifier
Dynamic: description
Dynamic: description-content-type
Dynamic: home-page
Dynamic: keywords
Dynamic: license-file
Dynamic: project-url
Dynamic: requires-dist
Dynamic: requires-python
Dynamic: summary
